MASShortcut/__init__.py
MASShortcut/_inlines.cpython-37m-darwin.so
MASShortcut/_metadata.py
pyobjc_MASShortcut-1.0a0.dist-info/METADATA
pyobjc_MASShortcut-1.0a0.dist-info/RECORD
pyobjc_MASShortcut-1.0a0.dist-info/WHEEL
pyobjc_MASShortcut-1.0a0.dist-info/top_level.txt
