Metadata-Version: 2.1
Name: pyobjc-MASShortcut
Version: 1.0a0
Summary: Wrappers for the library MASShortcut on macOS
Home-page: https://bitbucket.org/ronaldoussoren/pyobjc
Author: Ronald Oussoren
Author-email: pyobjc-dev@lists.sourceforge.net
License: MIT License
Keywords: PyObjC,MASShortcut
Platform: MacOS X (>=10.9)
Classifier: Development Status :: 5 - Production/Stable
Classifier: Environment :: Console
Classifier: Environment :: MacOS X :: Cocoa
Classifier: Intended Audience :: Developers
Classifier: License :: OSI Approved :: MIT License
Classifier: Natural Language :: English
Classifier: Operating System :: MacOS :: MacOS X
Classifier: Programming Language :: Python
Classifier: Programming Language :: Python :: 2
Classifier: Programming Language :: Python :: 2.7
Classifier: Programming Language :: Python :: 3
Classifier: Programming Language :: Python :: 3.4
Classifier: Programming Language :: Python :: 3.5
Classifier: Programming Language :: Python :: 3.6
Classifier: Programming Language :: Python :: 3.7
Classifier: Programming Language :: Python :: Implementation :: CPython
Classifier: Programming Language :: Objective C
Classifier: Topic :: Software Development :: Libraries :: Python Modules
Classifier: Topic :: Software Development :: User Interfaces
Project-URL: Issue tracker, https://bitbucket.org/ronaldoussoren/pyobjc-masshortcut/issues?status=new&status=open
Requires-Dist: pyobjc-core
Requires-Dist: pyobjc-framework-Cocoa
